algomancy_gui/__init__.py
algomancy_gui/admin_page/__init__.py
algomancy_gui/admin_page/admin.py
algomancy_gui/admin_page/sessions.py
algomancy_gui/appconfiguration.py
algomancy_gui/compare_page/__init__.py
algomancy_gui/compare_page/compare.py
algomancy_gui/compare_page/kpicard.py
algomancy_gui/compare_page/scenarioselector.py
algomancy_gui/componentids.py
algomancy_gui/contentregistry.py
algomancy_gui/cqmloader.py
algomancy_gui/data_page/__init__.py
algomancy_gui/data_page/data.py
algomancy_gui/data_page/datamanagementdeletemodal.py
algomancy_gui/data_page/datamanagementderivemodal.py
algomancy_gui/data_page/datamanagementdownloadmodal.py
algomancy_gui/data_page/datamanagementimportmodal.py
algomancy_gui/data_page/datamanagementsavemodal.py
algomancy_gui/data_page/datamanagementtopbar.py
algomancy_gui/data_page/datamanagementuploadmodal.py
algomancy_gui/data_page/dialogcallbacks.py
algomancy_gui/data_page/filenamematcher.py
algomancy_gui/defaultloader.py
algomancy_gui/gui_launcher.py
algomancy_gui/home_page/__init__.py
algomancy_gui/home_page/home.py
algomancy_gui/layout.py
algomancy_gui/layouthelpers.py
algomancy_gui/managergetters.py
algomancy_gui/overview_page/__init__.py
algomancy_gui/overview_page/overview.py
algomancy_gui/py.typed
algomancy_gui/scenario_page/__init__.py
algomancy_gui/scenario_page/delete_confirmation.py
algomancy_gui/scenario_page/new_scenario_creator.py
algomancy_gui/scenario_page/new_scenario_parameters_window.py
algomancy_gui/scenario_page/scenario_badge.py
algomancy_gui/scenario_page/scenario_cards.py
algomancy_gui/scenario_page/scenarios.py
algomancy_gui/sessionmanager.py
algomancy_gui/settingsmanager.py
algomancy_gui/stylingconfigurator.py
algomancy_gui-0.3.18.dist-info/WHEEL
algomancy_gui-0.3.18.dist-info/METADATA
algomancy_gui-0.3.18.dist-info/RECORD
