Metadata-Version: 2.3
Name: algomancy-gui
Version: 0.3.18
Summary: Dash components for the Algomancy library
Author: Pepijn Wissing
Author-email: Pepijn Wissing <Wsg@cqm.nl>
Requires-Dist: dash
Requires-Dist: dash-bootstrap-components
Requires-Dist: dash-auth>=2.3.0
Requires-Dist: algomancy-data
Requires-Dist: algomancy-scenario
Requires-Dist: algomancy-content
Requires-Dist: algomancy-utils
Requires-Dist: waitress>=3.0.2
Requires-Dist: strenum>=0.4.15
Requires-Python: >=3.14
